lsfiles/__init__.py
lsfiles/_indexing.py
lsfiles/_objects.py
lsfiles/_version.py
lsfiles/py.typed
lsfiles-0.5.1.dist-info/LICENSE
lsfiles-0.5.1.dist-info/METADATA
lsfiles-0.5.1.dist-info/WHEEL
lsfiles-0.5.1.dist-info/RECORD
