Metadata-Version: 2.1
Name: lsfiles
Version: 0.5.1
Summary: Path object VC index
Home-page: https://pypi.org/project/lsfiles/
License: MIT
Keywords: git,index,lsfiles,oop,vc
Author: jshwi
Author-email: stephen@jshwisolutions.com
Maintainer: jshwi
Maintainer-email: stephen@jshwisolutions.com
Requires-Python: >=3.8,<4.0
Classifier: License :: OSI Approved :: MIT License
Classifier: Programming Language :: Python :: 3
Classifier: Programming Language :: Python :: 3.8
Classifier: Programming Language :: Python :: 3.9
Classifier: Programming Language :: Python :: 3.10
Classifier: Programming Language :: Python :: 3.11
Requires-Dist: gitpython (>=3.1.33,<4.0.0)
Project-URL: Documentation, https://lsfiles.readthedocs.io/en/latest
Project-URL: Repository, https://github.com/jshwi/lsfiles
